talkshow/__init__.py
talkshow/cli/__init__.py
talkshow/cli/main.py
talkshow/config/__init__.py
talkshow/config/default.yaml
talkshow/config/manager.py
talkshow/models/__init__.py
talkshow/models/chat.py
talkshow/models/storage.py
talkshow/parser/__init__.py
talkshow/parser/md_parser.py
talkshow/parser/time_extractor.py
talkshow/storage/__init__.py
talkshow/storage/json_storage.py
talkshow/summarizer/__init__.py
talkshow/summarizer/llm_summarizer.py
talkshow/summarizer/rule_summarizer.py
talkshow/web/__init__.py
talkshow/web/app.py
talkshow/web/static/index.html
talkshow/web/static/script.js
talkshow/web/static/style.css
tests/__init__.py
tests/test_llm_summarizer.py
tests/test_moon.py
tests/test_parser.py
tests/test_storage.py
tests/test_summarizer.py
talkshow-0.1.3.dist-info/METADATA
talkshow-0.1.3.dist-info/WHEEL
talkshow-0.1.3.dist-info/entry_points.txt
talkshow-0.1.3.dist-info/top_level.txt
talkshow-0.1.3.dist-info/RECORD
