Metadata-Version: 2.4
Name: talkshow
Version: 0.1.3
Summary: Chat History Analysis and Visualization Tool
Home-page: https://github.com/cjhgo/talkshow
Author: TalkShow Team
Author-email: team@talkshow.dev
License: MIT
Project-URL: Bug Reports, https://github.com/cjhgo/talkshow/issues
Project-URL: Source, https://github.com/cjhgo/talkshow
Project-URL: Documentation, https://github.com/cjhgo/talkshow#readme
Keywords: chat,history,analysis,visualization,markdown,llm
Classifier: Development Status :: 3 - Alpha
Classifier: Intended Audience :: Developers
Classifier: License :: OSI Approved :: MIT License
Classifier: Operating System :: OS Independent
Classifier: Programming Language :: Python :: 3
Classifier: Programming Language :: Python :: 3.8
Classifier: Programming Language :: Python :: 3.9
Classifier: Programming Language :: Python :: 3.10
Classifier: Programming Language :: Python :: 3.11
Classifier: Programming Language :: Python :: 3.12
Classifier: Topic :: Software Development :: Documentation
Classifier: Topic :: Text Processing :: Markup
Classifier: Topic :: Scientific/Engineering :: Information Analysis
Classifier: Topic :: Text Processing :: Linguistic
Requires-Python: >=3.8
Requires-Dist: pytest>=7.0.0
Requires-Dist: pytest-cov>=4.0.0
Requires-Dist: litellm>=1.0.0
Requires-Dist: pyyaml>=6.0.0
Requires-Dist: click>=8.0.0
Requires-Dist: rich>=13.0.0
Requires-Dist: psutil>=5.9.0
Requires-Dist: fastapi>=0.100.0
Requires-Dist: uvicorn>=0.20.0
Requires-Dist: jinja2>=3.1.0
Provides-Extra: dev
Requires-Dist: pytest>=7.0.0; extra == "dev"
Requires-Dist: pytest-cov>=4.0.0; extra == "dev"
Provides-Extra: llm
Requires-Dist: litellm>=1.0.0; extra == "llm"
Provides-Extra: web
Requires-Dist: fastapi>=0.100.0; extra == "web"
Requires-Dist: uvicorn>=0.20.0; extra == "web"
Provides-Extra: cli
Requires-Dist: click>=8.0.0; extra == "cli"
Requires-Dist: rich>=13.0.0; extra == "cli"
Requires-Dist: pyyaml>=6.0.0; extra == "cli"
Requires-Dist: psutil>=5.9.0; extra == "cli"
Dynamic: author
Dynamic: author-email
Dynamic: classifier
Dynamic: description
Dynamic: description-content-type
Dynamic: home-page
Dynamic: keywords
Dynamic: license
Dynamic: project-url
Dynamic: provides-extra
Dynamic: requires-dist
Dynamic: requires-python
Dynamic: summary
